midi_velocity_mapper/__about__.py
midi_velocity_mapper/__init__.py
midi_velocity_mapper/translate_velocities.py
midi_velocity_mapper/util.py
midi_velocity_mapper/data/keys-all.tsv
midi_velocity_mapper/data/keys-black.tsv
midi_velocity_mapper/data/keys-white.tsv
midi_velocity_mapper-0.0.1.dist-info/METADATA
midi_velocity_mapper-0.0.1.dist-info/WHEEL
midi_velocity_mapper-0.0.1.dist-info/entry_points.txt
midi_velocity_mapper-0.0.1.dist-info/licenses/LICENSE.txt
midi_velocity_mapper-0.0.1.dist-info/RECORD
