Metadata-Version: 2.4
Name: midi-velocity-mapper
Version: 0.0.1
Summary: Translate MIDI note velocity data in real time
Project-URL: Documentation, https://github.com/phmccarty/midi-velocity-mapper#readme
Project-URL: Issues, https://github.com/phmccarty/midi-velocity-mapper/issues
Project-URL: Source, https://github.com/phmccarty/midi-velocity-mapper
Author-email: Patrick McCarty <pnorcks@gmail.com>
License-Expression: MIT
License-File: LICENSE.txt
Classifier: Development Status :: 4 - Beta
Classifier: Programming Language :: Python
Classifier: Programming Language :: Python :: 3.11
Classifier: Programming Language :: Python :: 3.12
Classifier: Programming Language :: Python :: Implementation :: CPython
Classifier: Programming Language :: Python :: Implementation :: PyPy
Requires-Python: >=3.11
Requires-Dist: mido[ports-rtmidi]
Requires-Dist: rich
